dc6006l/__init__.py
dc6006l-0.0.1.dist-info/LICENSE
dc6006l-0.0.1.dist-info/METADATA
dc6006l-0.0.1.dist-info/WHEEL
dc6006l-0.0.1.dist-info/entry_points.txt
dc6006l-0.0.1.dist-info/top_level.txt
dc6006l-0.0.1.dist-info/RECORD
