Metadata-Version: 2.1
Name: dc6006l
Version: 0.0.1
Summary: CLI/library to control FNIRSI DC Power Supply (DC-6006L, etc).
Home-page: https://github.com/tai/dc6006l/
Author: Taisuke Yamada
Author-email: tai@remove-if-not-spam.rakugaki.org
License: MIT
Platform: UNKNOWN
Classifier: License :: OSI Approved :: MIT License
Classifier: Intended Audience :: Developers
Classifier: Programming Language :: Python :: 2
Classifier: Programming Language :: Python :: 2.7
Classifier: Programming Language :: Python :: 3
Classifier: Topic :: Scientific/Engineering
Classifier: Topic :: Software Development :: Embedded Systems
Classifier: Topic :: System :: Hardware
Requires-Dist: pyserial
Requires-Dist: argparse
